aliyunsdkclickhouse/__init__.py
aliyunsdkclickhouse/endpoint.py
aliyunsdkclickhouse/request/__init__.py
aliyunsdkclickhouse/request/v20191111/AllocateClusterPublicConnectionRequest.py
aliyunsdkclickhouse/request/v20191111/CheckClickhouseToRDSRequest.py
aliyunsdkclickhouse/request/v20191111/CheckModifyConfigNeedRestartRequest.py
aliyunsdkclickhouse/request/v20191111/CheckMonitorAlertRequest.py
aliyunsdkclickhouse/request/v20191111/CheckScaleOutBalancedRequest.py
aliyunsdkclickhouse/request/v20191111/CheckServiceLinkedRoleRequest.py
aliyunsdkclickhouse/request/v20191111/CreateAccountAndAuthorityRequest.py
aliyunsdkclickhouse/request/v20191111/CreateAccountRequest.py
aliyunsdkclickhouse/request/v20191111/CreateBackupPolicyRequest.py
aliyunsdkclickhouse/request/v20191111/CreateDBInstanceRequest.py
aliyunsdkclickhouse/request/v20191111/CreateMonitorDataReportRequest.py
aliyunsdkclickhouse/request/v20191111/CreateOSSStorageRequest.py
aliyunsdkclickhouse/request/v20191111/CreatePortsForClickHouseRequest.py
aliyunsdkclickhouse/request/v20191111/CreateRDSToClickhouseDbRequest.py
aliyunsdkclickhouse/request/v20191111/CreateSQLAccountRequest.py
aliyunsdkclickhouse/request/v20191111/CreateServiceLinkedRoleRequest.py
aliyunsdkclickhouse/request/v20191111/DeleteAccountRequest.py
aliyunsdkclickhouse/request/v20191111/DeleteDBClusterRequest.py
aliyunsdkclickhouse/request/v20191111/DeleteSyndbRequest.py
aliyunsdkclickhouse/request/v20191111/DescribeAccountAuthorityRequest.py
aliyunsdkclickhouse/request/v20191111/DescribeAccountsRequest.py
aliyunsdkclickhouse/request/v20191111/DescribeAllDataSourceRequest.py
aliyunsdkclickhouse/request/v20191111/DescribeAllDataSourcesRequest.py
aliyunsdkclickhouse/request/v20191111/DescribeBackupPolicyRequest.py
aliyunsdkclickhouse/request/v20191111/DescribeBackupsRequest.py
aliyunsdkclickhouse/request/v20191111/DescribeColumnsRequest.py
aliyunsdkclickhouse/request/v20191111/DescribeConfigHistoryRequest.py
aliyun_python_sdk_clickhouse-3.1.6.dist-info/LICENSE
aliyun_python_sdk_clickhouse-3.1.6.dist-info/METADATA
aliyun_python_sdk_clickhouse-3.1.6.dist-info/WHEEL
aliyun_python_sdk_clickhouse-3.1.6.dist-info/top_level.txt
aliyun_python_sdk_clickhouse-3.1.6.dist-info/RECORD
